{
  "schemaVersion": 1,
  "status": "active",
  "model": "v14",
  "formulaVersion": "v14.0.0",
  "benchmark": "SPY",
  "topN": 20,
  "rebalanceSchedule": "monthly",
  "transactionCostBps": 10.0,
  "initialValue": 10000.0,
  "inceptionDate": "2026-07-01",
  "lastRebalanceDate": "2026-07-01",
  "lastUpdated": "2026-07-02T08:29:02+00:00",
  "latestSnapshot": "public/data/history/2026-07-02.json",
  "cumulativeCosts": 10.0,
  "benchmarkStartPrice": 748.98,
  "positions": [
    {
      "ticker": "HON",
      "name": "Honeywell International Inc.",
      "sector": "industrial",
      "shares": 2.620525414841644,
      "targetWeight": 0.05875590467170969,
      "entryPrice": 223.99,
      "lastPrice": 221.75,
      "entryScore": 24.055141538939026,
      "lastScore": 24.130492785204975,
      "enteredDate": "2026-07-01"
    },
    {
      "ticker": "EOG",
      "name": "EOG Resources, Inc.",
      "sector": "energy",
      "shares": 4.397366659130483,
      "targetWeight": 0.05665516143109955,
      "entryPrice": 128.71,
      "lastPrice": 128.59,
      "entryScore": 22.51327581463428,
      "lastScore": 22.55854106460792,
      "enteredDate": "2026-07-01"
    },
    {
      "ticker": "PCG",
      "name": "Pacific Gas & Electric Co.",
      "sector": "other",
      "shares": 33.7673766214523,
      "targetWeight": 0.05628572127131369,
      "entryPrice": 16.652,
      "lastPrice": 16.57,
      "entryScore": 22.323819259374307,
      "lastScore": 22.523485559266717,
      "enteredDate": "2026-07-01"
    },
    {
      "ticker": "GILD",
      "name": "Gilead Sciences, Inc.",
      "sector": "healthcare",
      "shares": 4.336713256591535,
      "targetWeight": 0.05474937696910154,
      "entryPrice": 126.12,
      "lastPrice": 125.97,
      "entryScore": 21.53595012419659,
      "lastScore": 21.594731937987117,
      "enteredDate": "2026-07-01"
    },
    {
      "ticker": "REGN",
      "name": "Regeneron Pharmaceuticals, Inc.",
      "sector": "healthcare",
      "shares": 0.8598243764978468,
      "targetWeight": 0.05409749885925492,
      "entryPrice": 628.54,
      "lastPrice": 624.72,
      "entryScore": 21.20165354633534,
      "lastScore": 21.49880023784384,
      "enteredDate": "2026-07-01"
    },
    {
      "ticker": "COP",
      "name": "ConocoPhillips",
      "sector": "energy",
      "shares": 5.121144503501317,
      "targetWeight": 0.05326195334472342,
      "entryPrice": 103.9,
      "lastPrice": 103.22,
      "entryScore": 20.773168524463824,
      "lastScore": 21.050839135940237,
      "enteredDate": "2026-07-01"
    },
    {
      "ticker": "BSX",
      "name": "Boston Scientific Corporation",
      "sector": "healthcare",
      "shares": 12.32995723297382,
      "targetWeight": 0.053090401439075965,
      "entryPrice": 43.015,
      "lastPrice": 43.06,
      "entryScore": 20.68519315895107,
      "lastScore": 20.660468286741338,
      "enteredDate": "2026-07-01"
    },
    {
      "ticker": "OXY",
      "name": "Occidental Petroleum Corporatio",
      "sector": "energy",
      "shares": 10.533013958282815,
      "targetWeight": 0.05078831655360192,
      "entryPrice": 48.17,
      "lastPrice": 47.94,
      "entryScore": 19.50463641446836,
      "lastScore": 19.723662202249812,
      "enteredDate": "2026-07-01"
    },
    {
      "ticker": "SCHW",
      "name": "Charles Schwab Corporation (The",
      "sector": "financial",
      "shares": 5.114266998757618,
      "targetWeight": 0.048920856296424224,
      "entryPrice": 95.56,
      "lastPrice": 95.78,
      "entryScore": 19.011525308703416,
      "lastScore": 18.893915298010576,
      "enteredDate": "2026-07-01"
    },
    {
      "ticker": "T",
      "name": "AT&T Inc.",
      "sector": "software",
      "shares": 24.04722391254407,
      "targetWeight": 0.049671117661195884,
      "entryPrice": 20.635,
      "lastPrice": 20.48,
      "entryScore": 18.93171371484038,
      "lastScore": 19.23115636111443,
      "enteredDate": "2026-07-01"
    },
    {
      "ticker": "PDD",
      "name": "PDD Holdings Inc.",
      "sector": "consumer",
      "shares": 5.9080455865947705,
      "targetWeight": 0.048547693914270745,
      "entryPrice": 82.09,
      "lastPrice": 82.52,
      "entryScore": 18.355598781063122,
      "lastScore": 18.168739448480036,
      "enteredDate": "2026-07-01"
    },
    {
      "ticker": "ICE",
      "name": "Intercontinental Exchange Inc.",
      "sector": "financial",
      "shares": 3.7381376664049837,
      "targetWeight": 0.047604191583587786,
      "entryPrice": 127.22,
      "lastPrice": 126.73,
      "entryScore": 18.33631241070406,
      "lastScore": 18.42152451542986,
      "enteredDate": "2026-07-01"
    },
    {
      "ticker": "SLB",
      "name": "SLB Limited",
      "sector": "energy",
      "shares": 10.31947860816234,
      "targetWeight": 0.047429315344722105,
      "entryPrice": 45.915,
      "lastPrice": 45.09,
      "entryScore": 18.104098184946178,
      "lastScore": 18.852894511270847,
      "enteredDate": "2026-07-01"
    },
    {
      "ticker": "ROST",
      "name": "Ross Stores, Inc.",
      "sector": "consumer",
      "shares": 2.2170070104796404,
      "targetWeight": 0.047023184729782876,
      "entryPrice": 211.89,
      "lastPrice": 211.9,
      "entryScore": 18.03836007880783,
      "lastScore": 18.035864193545446,
      "enteredDate": "2026-07-01"
    },
    {
      "ticker": "TMUS",
      "name": "T-Mobile US, Inc.",
      "sector": "software",
      "shares": 2.7343812317230243,
      "targetWeight": 0.04715918061258443,
      "entryPrice": 172.295,
      "lastPrice": 173.06,
      "entryScore": 17.643540440620047,
      "lastScore": 17.467957331921728,
      "enteredDate": "2026-07-01"
    },
    {
      "ticker": "TJX",
      "name": "TJX Companies, Inc. (The)",
      "sector": "consumer",
      "shares": 3.0629404688574127,
      "targetWeight": 0.04636261691674411,
      "entryPrice": 151.215,
      "lastPrice": 151.35,
      "entryScore": 17.23504610165447,
      "lastScore": 17.168974637398808,
      "enteredDate": "2026-07-01"
    },
    {
      "ticker": "VZ",
      "name": "Verizon Communications Inc.",
      "sector": "software",
      "shares": 10.786092042436579,
      "targetWeight": 0.04545490240105906,
      "entryPrice": 42.1,
      "lastPrice": 41.99,
      "entryScore": 16.76955132328266,
      "lastScore": 16.93354449498023,
      "enteredDate": "2026-07-01"
    },
    {
      "ticker": "MSFT",
      "name": "Microsoft Corporation",
      "sector": "ai",
      "shares": 1.1482190535873524,
      "targetWeight": 0.04440814772117572,
      "entryPrice": 386.37,
      "lastPrice": 384.28,
      "entryScore": 16.697315012631936,
      "lastScore": 16.826555696572328,
      "enteredDate": "2026-07-01"
    },
    {
      "ticker": "FANG",
      "name": "Diamondback Energy, Inc.",
      "sector": "energy",
      "shares": 2.583804325413851,
      "targetWeight": 0.04512605201967785,
      "entryPrice": 174.475,
      "lastPrice": 171.96,
      "entryScore": 16.600910045927954,
      "lastScore": 17.253934958650387,
      "enteredDate": "2026-07-01"
    },
    {
      "ticker": "AZN",
      "name": "AstraZeneca PLC",
      "sector": "healthcare",
      "shares": 2.4130931556862363,
      "targetWeight": 0.044608406258894465,
      "entryPrice": 184.675,
      "lastPrice": 183.86,
      "entryScore": 16.335450593063396,
      "lastScore": 16.61203645764769,
      "enteredDate": "2026-07-01"
    }
  ],
  "rebalanceHistory": [
    {
      "date": "2026-07-01",
      "reason": "inception",
      "turnover": 1.0,
      "transactionCost": 10.0,
      "tickers": [
        "HON",
        "EOG",
        "PCG",
        "GILD",
        "REGN",
        "COP",
        "BSX",
        "OXY",
        "SCHW",
        "T",
        "PDD",
        "ICE",
        "SLB",
        "ROST",
        "TMUS",
        "TJX",
        "VZ",
        "MSFT",
        "FANG",
        "AZN"
      ]
    }
  ],
  "history": [
    {
      "date": "2026-07-01",
      "snapshotTime": "2026-07-01T17:01:24+00:00",
      "portfolioValue": 9983.079661067137,
      "benchmarkValue": 9984.111725279714,
      "portfolioReturn": -0.0016920338932863155,
      "benchmarkReturn": -0.0015888274720285978,
      "excessReturn": -0.00010320642125771773,
      "transactionCost": 0.0,
      "rebalanced": false
    },
    {
      "date": "2026-07-02",
      "snapshotTime": "2026-07-02T08:29:02+00:00",
      "portfolioValue": 9951.617557940635,
      "benchmarkValue": 9957.008197815696,
      "portfolioReturn": -0.004838244205936482,
      "benchmarkReturn": -0.004299180218430454,
      "excessReturn": -0.0005390639875060277,
      "transactionCost": 0.0,
      "rebalanced": false
    }
  ],
  "summary": {
    "portfolioValue": 9951.617557940635,
    "benchmarkValue": 9957.008197815696,
    "portfolioReturn": -0.004838244205936482,
    "benchmarkReturn": -0.004299180218430454,
    "excessReturn": -0.0005390639875060277,
    "maxDrawdown": 0.003151542829934539,
    "evidenceDays": 2
  },
  "requiresReset": false
}
